craft_providers/__init__.py
craft_providers/_version.py
craft_providers/base.py
craft_providers/const.py
craft_providers/errors.py
craft_providers/executor.py
craft_providers/hookutil.py
craft_providers/instance_config.py
craft_providers/provider.py
craft_providers/py.typed
craft_providers/actions/__init__.py
craft_providers/actions/snap_installer.py
craft_providers/bases/__init__.py
craft_providers/bases/almalinux.py
craft_providers/bases/centos.py
craft_providers/bases/checks.py
craft_providers/bases/errors.py
craft_providers/bases/ubuntu.py
craft_providers/data/__init__.py
craft_providers/data/ubuntu.csv
craft_providers/lxd/__init__.py
craft_providers/lxd/errors.py
craft_providers/lxd/installer.py
craft_providers/lxd/launcher.py
craft_providers/lxd/lxc.py
craft_providers/lxd/lxd.py
craft_providers/lxd/lxd_instance.py
craft_providers/lxd/lxd_instance_status.py
craft_providers/lxd/lxd_provider.py
craft_providers/lxd/project.py
craft_providers/lxd/remotes.py
craft_providers/multipass/__init__.py
craft_providers/multipass/_launch.py
craft_providers/multipass/_ready.py
craft_providers/multipass/errors.py
craft_providers/multipass/installer.py
craft_providers/multipass/multipass.py
craft_providers/multipass/multipass_instance.py
craft_providers/multipass/multipass_provider.py
craft_providers/util/__init__.py
craft_providers/util/env_cmd.py
craft_providers/util/os_release.py
craft_providers/util/retry.py
craft_providers/util/snap_cmd.py
craft_providers/util/sources.sh
craft_providers/util/temp_paths.py
craft_providers-3.2.0.dist-info/licenses/LICENSE
craft_providers_docs/.gitkeep
craft_providers-3.2.0.dist-info/METADATA
craft_providers-3.2.0.dist-info/WHEEL
craft_providers-3.2.0.dist-info/entry_points.txt
craft_providers-3.2.0.dist-info/top_level.txt
craft_providers-3.2.0.dist-info/RECORD
