Metadata-Version: 2.4
Name: craft-providers
Version: 3.2.0
License:                    GNU LESSER GENERAL PUBLIC LICENSE
Classifier: Development Status :: 5 - Production/Stable
Classifier: Intended Audience :: Developers
Classifier: Natural Language :: English
Classifier: Operating System :: MacOS :: MacOS X
Classifier: Operating System :: POSIX :: Linux
Classifier: Programming Language :: Python :: 3.10
Classifier: Programming Language :: Python :: 3.11
Classifier: Programming Language :: Python :: 3.12
Classifier: Topic :: Software Development :: Libraries
Classifier: Topic :: Software Development :: Libraries :: Python Modules
Requires-Python: >=3.10
License-File: LICENSE
Requires-Dist: packaging>=14.1
Requires-Dist: pydantic~=2.4
Requires-Dist: pylxd>=2.3.5
Requires-Dist: pyyaml
Requires-Dist: requests>=2.31
Requires-Dist: requests_unixsocket2>=0.4.0
Dynamic: license-file
